com_enovation/__init__.py
com_enovation/enov.py
com_enovation/helper/__init__.py
com_enovation/helper/excel_loader.py
com_enovation/helper/json_encoder.py
com_enovation/helper/pandas_dataframe_sampler.py
com_enovation/helper/pandas_dataframe_typer.py
com_enovation/helper/click/__init__.py
com_enovation/helper/click/debug.py
com_enovation/helper/click/df_load.py
com_enovation/helper/click/df_modify.py
com_enovation/helper/click/df_write.py
com_enovation/helper/click/dict_load_modify_write.py
com_enovation/helper/click/enov_group.py
com_enovation/helper/click/py_exec.py
com_enovation/helper/click/python_literal_argument_and_option.py
com_enovation/helper/excel/__init__.py
com_enovation/helper/excel/xls_data_connection_to_df.py
com_enovation/helper/excel/xls_refresh_data_connections.py
com_enovation/helper/excel/click/__init__.py
com_enovation/helper/excel/click/xls_data_connection_to_df_click.py
com_enovation/helper/excel/click/xls_refresh_data_connections_click.py
com_enovation/toolbox/__init__.py
com_enovation/toolbox/backlog/__init__.py
com_enovation/toolbox/backlog/bck_compare/__init__.py
com_enovation/toolbox/backlog/bck_compare/bck_comparer.py
com_enovation/toolbox/backlog/bck_compare/bck_delta.py
com_enovation/toolbox/dash/__init__.py
com_enovation/toolbox/dash/application.py
com_enovation/toolbox/dash/session.py
com_enovation/toolbox/dash/sheet.py
com_enovation/toolbox/dash/widget.py
com_enovation/toolbox/dash/click/__init__.py
com_enovation/toolbox/dash/click/ds_dash.py
com_enovation/toolbox/dash/layout/__init__.py
com_enovation/toolbox/dash/layout/debug/__init__.py
com_enovation/toolbox/dash/layout/debug/debug__as_div.py
com_enovation/toolbox/dash/layout/footer/__init__.py
com_enovation/toolbox/dash/layout/footer/footer__as_footer.py
com_enovation/toolbox/dash/layout/layout/__init__.py
com_enovation/toolbox/dash/layout/layout/layout__as_div.py
com_enovation/toolbox/dash/layout/navigation/__init__.py
com_enovation-0.0.40.dist-info/METADATA
com_enovation-0.0.40.dist-info/WHEEL
com_enovation-0.0.40.dist-info/entry_points.txt
com_enovation-0.0.40.dist-info/licenses/LICENSE
com_enovation-0.0.40.dist-info/RECORD
