Metadata-Version: 2.1
Name: com_enovation
Version: 0.0.40
Summary: project management toolbox
Project-URL: Homepage, https://jsebastien_Guillard@bitbucket.org/jsebastien_Guillard
Project-URL: Bug Tracker, https://jsebastien_Guillard@bitbucket.org/jsebastien_Guillard
Author-email: jean-sebastien guillard <jsebastien.guillard@gmail.com>
License-File: LICENSE
Classifier: License :: Other/Proprietary License
Classifier: Operating System :: OS Independent
Classifier: Programming Language :: Python :: 3
Requires-Python: >=3.11
Requires-Dist: click
Requires-Dist: dash
Requires-Dist: dash-bootstrap-components
Requires-Dist: dash-extensions
Requires-Dist: enlighten
Requires-Dist: flask-caching
Requires-Dist: jsonschema
Requires-Dist: openpyxl
Requires-Dist: pandas
Requires-Dist: scipy
Requires-Dist: xlrd
Requires-Dist: xlsxwriter
Requires-Dist: xlwt
